restconf_sdk/__init__.py
restconf_sdk/restconf_requests.py
restconf_sdk/devices/__init__.py
restconf_sdk/devices/ios_xe.py
restconf_sdk-0.0.1.dist-info/METADATA
restconf_sdk-0.0.1.dist-info/WHEEL
restconf_sdk-0.0.1.dist-info/top_level.txt
restconf_sdk-0.0.1.dist-info/RECORD
